pybascule/__init__.py
pybascule/run.py
pybascule/simulation.py
pybascule/svi.py
pybascule/svi_mixture.py
pybascule-1.0.1.dist-info/LICENSE
pybascule-1.0.1.dist-info/METADATA
pybascule-1.0.1.dist-info/WHEEL
pybascule-1.0.1.dist-info/top_level.txt
pybascule-1.0.1.dist-info/RECORD
